{"slides":[{"type":"Text","text":"This is a project about the shared DNA in music. Orchestral music for a play in 1875 can become electronic music for a cartoon in 1983.","controller":{"focusNode":"64739","fitViewNodes":"64739,253610","visibleNodes":"64739,253610","component":{"id":"64739_253610","type":"crossfade"}}},{"type":"Text","text":"Which can be transformed by a minor rap group…","controller":{"focusNode":"253610","fitViewNodes":"64739,253610","visibleNodes":"64739,253610","component":{"id":"64739_253610","type":"crossfade"}}},{"type":"Text","text":"","controller":{"focusNode":"253610","fitViewNodes":"253610,234958","visibleNodes":"64739,253610,253610,234958","component":{"id":"253610_234958","type":"crossfade"}}},{"type":"Text","text":"…and then influence the breakout hit of a rap giant….","controller":{"focusNode":"234958","fitViewNodes":"253610,234958","visibleNodes":"64739,253610,253610,234958","component":{"id":"253610_234958","type":"crossfade"}}},{"type":"Text","text":"We can see the full impact of sampling if we look at how sound is passed down and forms a musical lineage.","controller":{"fitViewNodes":"64739,253610,234958,234780,234899,233667","visibleNodes":"64739,253610,234958,234780,234899,233667","nodeHorizontalGap":"0","secondaryLabelAccessor":"lineage"}},{"type":"Text","text":"Hit Em Up has more lineages...","controller":{"focusNode":"234958","fitViewNodes":"64739,253610,234958,234780,234899,233667,232157","visibleNodes":"64739,253610,234958,234780,234899,233667,232157","nodeHorizontalGap":"0"}}]}